INSTALL
LICENSE
README
ez_setup.py
setup.py
Pyrex/Debugging.py
Pyrex/Utils.py
Pyrex/__init__.py
Pyrex/Compiler/.#Parsing.py.1.2
Pyrex/Compiler/CmdLine.py
Pyrex/Compiler/Code.py
Pyrex/Compiler/DebugFlags.py
Pyrex/Compiler/Errors.py
Pyrex/Compiler/ExprNodes.py
Pyrex/Compiler/Lexicon.pickle
Pyrex/Compiler/Lexicon.py
Pyrex/Compiler/Main.py
Pyrex/Compiler/Naming.py
Pyrex/Compiler/Nodes.py
Pyrex/Compiler/Options.py
Pyrex/Compiler/Parsing.py
Pyrex/Compiler/Parsing.py.patch
Pyrex/Compiler/PyrexTypes.py
Pyrex/Compiler/Scanning.py
Pyrex/Compiler/Symtab.py
Pyrex/Compiler/TypeSlots.py
Pyrex/Compiler/Version.py
Pyrex/Compiler/__init__.py
Pyrex/Distutils/__init__.py
Pyrex/Distutils/build_ext.py
Pyrex/Distutils/extension.py
Pyrex/Mac/DarwinSystem.py
Pyrex/Mac/Finder_Std_Suite.py
Pyrex/Mac/MPW_Misc_Suite.py
Pyrex/Mac/MacSystem.py
Pyrex/Mac/MacUtils.py
Pyrex/Mac/PS_Misc_Suite.py
Pyrex/Mac/PyServerMain.py
Pyrex/Mac/TS_Misc_Suite.py
Pyrex/Mac/_Filemodule_patched.c
Pyrex/Mac/__init__.py
Pyrex/Plex/Actions.py
Pyrex/Plex/DFA.py
Pyrex/Plex/Errors.py
Pyrex/Plex/Lexicons.py
Pyrex/Plex/Machines.py
Pyrex/Plex/Regexps.py
Pyrex/Plex/Scanners.py
Pyrex/Plex/Timing.py
Pyrex/Plex/Traditional.py
Pyrex/Plex/Transitions.py
Pyrex/Plex/__init__.py
Pyrex/Plex/test_tm.py
api/class-tree.html
api/crarr.png
api/epydoc.css
api/epydoc.js
api/frames.html
api/help.html
api/identifier-index.html
api/index.html
api/module-tree.html
api/mysql-module.html
api/mysql-pysrc.html
api/mysql.connection-module.html
api/mysql.connection.Character_Set-class.html
api/mysql.connection.Connection-class.html
api/mysql.connection._Statement_Cleaner-class.html
api/mysql.constants-module.html
api/mysql.constants-pysrc.html
api/mysql.constants.client_flags-module.html
api/mysql.constants.field_flags-module.html
api/mysql.constants.field_types-module.html
api/mysql.conversion-module.html
api/mysql.conversion-pysrc.html
api/mysql.conversion.input-module.html
api/mysql.conversion.input-pysrc.html
mysql_pyrex.egg-info/PKG-INFO
mysql_pyrex.egg-info/SOURCES.txt
mysql_pyrex.egg-info/dependency_links.txt
mysql_pyrex.egg-info/top_level.txt
