Metadata-Version: 1.0
Name: mysql-pyrex
Version: 0.9.0a1
Summary: Pyrex interface to the MySQL 5 API.
Home-page: http://ehuss.org/mysql/
Author: Eric Huss
Author-email: eric@ehuss.org
License: BSD
Platform: UNKNOWN
Classifier: Development Status :: 3 - Alpha
Classifier: License :: OSI Approved :: BSD License
Classifier: Topic :: Database
